{"meta":{"buildId":"A14vvPLK","url":"https://www.lastepochtools.com/planner/A14vvPLK","title":"Beastmaster, level 100 (Season 4: Shattered Omens) - Last Epoch Build Planner","scrapedAt":"2026-04-20T14:13:43.632Z"},"tabs":{"General":[{"header":"Attributes (253 total)","type":"kv","rows":[["Strength","105"],["Dexterity","18"],["Intelligence","105"],["Attunement","17"],["Vitality","8"]]},{"header":"Common","type":"kv","rows":[["Health","4494"],["Mana","241.7"],["Health Regen","592"],["Mana Regen","9.28"],["Movement Speed","78%"]]},{"header":"Resistances","type":"kv","rows":[["Fire Resistance","80%"],["Cold Resistance","113%"],["Lightning Resistance","89%"],["Physical Resistance","125%"],["Necrotic Resistance","95%"],["Poison Resistance","39%"],["Void Resistance","96%"]]},{"header":"Additional Defenses","type":"kv","rows":[["Dodge Rating","72"],["Dodge Chance","3%"],["Armor","3872"],["Armor Mitigation","56%"],["Block Chance","0%"],["Block Effectiveness","0"],["Block Mitigation","0%"]]}],"Offense":[{"header":"","type":"matrix","text":"Melee\nSpell\nBow\nThrowing\nDoT\nAttack Speed\n20%\n–\n20%\n20%\n–\nCast Speed\n–\n20%\n–\n–\n–"},{"header":"","type":"matrix","text":"Melee\nSpell\nBow\nThrowing\nDoT\nCritical Chance\n15%\n15%\n15%\n15%\n–\nCritical Multiplier\n269%\n269%\n269%\n269%\n–"},{"header":"Damage","type":"matrix","text":"Damage\nMelee\nSpell\nBow\nThrowing\nDoT\nAdaptive Damage\n39\n1\n0\n0\n0"},{"header":"","type":"matrix","text":"Melee\nSpell\nBow\nThrowing\nDoT\n+ Physical Damage\n101\n0\n0\n0\n0\n% Physical Damage\n52%\n126%\n2%\n2%\n6%\n+ Fire Damage\n0\n0\n0\n0\n0\n% Fire Damage\n52%\n126%\n2%\n2%\n6%\n+ Cold Damage\n0\n0\n0\n0\n0\n% Cold Damage\n52%\n126%\n2%\n2%\n6%\n+ Lightning Damage\n0\n0\n0\n0\n0\n% Lightning Damage\n52%\n126%\n2%\n2%\n6%\n+ Necrotic Damage\n0\n0\n0\n0\n0\n% Necrotic Damage\n52%\n126%\n2%\n2%\n6%\n+ Void Damage\n0\n5\n0\n0\n0\n% Void Damage\n105%\n179%\n55%\n55%\n59%\n+ Poison Damage\n0\n0\n0\n0\n0\n% Poison Damage\n52%\n126%\n2%\n2%\n6%\n+ Curse Damage\n0\n0\n0\n0\n0\n% Curse Damage\n52%\n126%\n2%\n2%\n6%"},{"header":"Ailments","type":"matrix","text":"Ailments\nMelee\nSpell\nBow\nThrowing\nDoT\nBleed Chance\n33%\n33%\n33%\n33%\n33%\nBleed Damage\n56\n56\n56\n56\n56\nBleed Duration\n0%\n0%\n0%\n0%\n0%\nPoison Chance\n0%\n0%\n0%\n0%\n0%\nPoison Damage\n30\n30\n30\n30\n30\nPoison Duration\n0%\n0%\n0%\n0%\n0%\nIgnite Chance\n0%\n0%\n0%\n0%\n0%\nIgnite Damage\n42\n42\n42\n42\n42\nIgnite Duration\n0%\n0%\n0%\n0%\n0%\nFrostbite Chance\n0%\n0%\n0%\n0%\n0%\nFrostbite Damage\n53\n53\n53\n53\n53\nFrostbite Duration\n0%\n0%\n0%\n0%\n0%\nElectrify Chance\n0%\n0%\n0%\n0%\n0%\nElectrify Damage\n47\n47\n47\n47\n47\nElectrify Duration\n0%\n0%\n0%\n0%\n0%\nDoom Chance\n0%\n0%\n0%\n0%\n0%\nDoom Damage\n636\n636\n636\n636\n636\nDoom Duration\n0%\n0%\n0%\n0%\n0%\nDamned Chance\n0%\n0%\n0%\n0%\n0%\nDamned Damage\n37\n37\n37\n37\n37\nDamned Duration\n0%\n0%\n0%\n0%\n0%\nTime Rot Chance\n0%\n0%\n0%\n0%\n0%\nTime Rot Damage\n95\n95\n95\n95\n95\nTime Rot Duration\n0%\n0%\n0%\n0%\n0%\nWitchfire Chance\n0%\n0%\n0%\n0%\n0%\nWitchfire Damage\n636\n636\n636\n636\n636\nWitchfire Duration\n0%\n0%\n0%\n0%\n0%\nPlague Chance\n0%\n0%\n0%\n0%\n0%\nPlague Damage\n159\n159\n159\n159\n159\nPlague Duration\n0%\n0%\n0%\n0%\n0%\nShock Chance\n0%\n0%\n0%\n0%\n0%\nShock Duration\n0%\n0%\n0%\n0%\n0%\nSlow Chance\n0%\n0%\n0%\n0%\n0%\nSlow Duration\n0%\n0%\n0%\n0%\n0%\nBlind Chance\n0%\n0%\n0%\n0%\n0%\nBlind Duration\n0%\n0%\n0%\n0%\n0%\nFrailty Chance\n0%\n0%\n0%\n0%\n0%\nFrailty Duration\n0%\n0%\n0%\n0%\n0%\nShred Armor Chance\n0%\n0%\n0%\n0%\n0%\nShred Armor Effect\n0%\n0%\n0%\n0%\n0%\nShred Armor Duration\n0%\n0%\n0%\n0%\n0%\nShred Fire Resistance Chance\n0%\n0%\n0%\n0%\n0%\nShred Fire Resistance Effect\n0%\n0%\n0%\n0%\n0%\nShred Fire Resistance Duration\n0%\n0%\n0%\n0%\n0%\nShred Cold Resistance Chance\n0%\n0%\n0%\n0%\n0%\nShred Cold Resistance Effect\n0%\n0%\n0%\n0%\n0%\nShred Cold Resistance Duration\n0%\n0%\n0%\n0%\n0%\nShred Lightning Resistance Chance\n0%\n0%\n0%\n0%\n0%\nShred Lightning Resistance Effect\n0%\n0%\n0%\n0%\n0%\nShred Lightning Resistance Duration\n0%\n0%\n0%\n0%\n0%\nShred Physical Resistance Chance\n0%\n0%\n0%\n0%\n0%\nShred Physical Resistance Effect\n0%\n0%\n0%\n0%\n0%\nShred Physical Resistance Duration\n0%\n0%\n0%\n0%\n0%\nShred Necrotic Resistance Chance\n0%\n0%\n0%\n0%\n0%\nShred Necrotic Resistance Effect\n0%\n0%\n0%\n0%\n0%\nShred Necrotic Resistance Duration\n0%\n0%\n0%\n0%\n0%\nShred Poison Resistance Chance\n0%\n0%\n0%\n0%\n0%\nShred Poison Resistance Effect\n0%\n0%\n0%\n0%\n0%\nShred Poison Resistance Duration\n0%\n0%\n0%\n0%\n0%\nShred Void Resistance Chance\n0%\n0%\n0%\n0%\n0%\nShred Void Resistance Effect\n0%\n0%\n0%\n0%\n0%\nShred Void Resistance Duration\n0%\n0%\n0%\n0%\n0%\nChill Chance\n6%\n6%\n6%\n6%\n6%\nChill Duration\n0%\n0%\n0%\n0%\n0%\nFreeze Rate Multiplier\n0%\n0%\n0%\n0%\n0%"},{"header":"Other","type":"matrix","text":"Other\nMelee\nSpell\nBow\nThrowing\nDoT\n% Stun Chance\n0%\n0%\n0%\n0%\n–\n% Stun Duration\n0%\n0%\n0%\n0%\n–"}],"Defense":[{"header":"","type":"kv","rows":[["Endurance","55%"],["Endurance Threshold","1339"],["Glancing Blow Chance","0%"],["Critical Strike Avoidance","0%"],["Reduced Bonus Damage Taken From Critical Strikes","27%"],["Parry Chance","0%"],["Ward Regen","193"],["Ward Retention","276%"],["Ward Decay Threshold","34"]]},{"header":"","type":"kv","rows":[["Damage Taken","8%"],["Damage Over Time Taken","8%"],["Damage Taken While Moving","0%"],["Damage Taken From Nearby Enemies","-16%"],["Damage Dealt To Mana Before Health","0%"],["Damage Dealt To Mana Before Ward","0%"],["Stun Avoidance","285"]]},{"header":"Effective Health Pool","type":"matrix","text":"Effective Health Pool\nEHP vs Hit\nEHP vs DoT\nEHP vs one-shot\nPhysical Damage\n15885\n6758\n15463\nFire Damage\n11457\n6758\n11153\nCold Damage\n11457\n6758\n11153\nLightning Damage\n11457\n6758\n11153\nNecrotic Damage\n11457\n6758\n11153\nVoid Damage\n11457\n6758\n11153\nPoison Damage\n8424\n4969\n8201"},{"header":"Health Gain / Health Leech","type":"matrix","text":"Health Gain / Health Leech\nMelee\nSpell\nBow\nThrowing\nDoT\nHealth Leech\n0%\n0%\n0%\n0%\n0%"},{"header":"","type":"kv","rows":[["Health Gain on Hit","0"],["Health Gain on Melee Hit","0"],["Health Gain on Kill","36"],["Health Gain on Block","0"],["Health Gain on Stun","0"],["Health Gain on Freeze","0"],["Health Gain on Crit","0"]]},{"header":"","type":"kv","rows":[["Overkill Health Leech","0%"],["Increased Leech Rate","0%"]]}],"Minion":[{"header":"","type":"kv","rows":[["Maximum Companions","7"],["Minion Power From Character Level","60%"],["Increased Health","38%"],["Health Regen","0"],["Increased Health Regen","0%"]]},{"header":"","type":"kv","rows":[["Dodge Rating","0"],["Armor","0"],["Critical Strike Avoidance","0%"],["Reduced Bonus Damage Taken From Critical Strikes","15%"],["Movement Speed","80%"]]},{"header":"","type":"kv","rows":[["Fire Resistance","19%"],["Cold Resistance","73%"],["Lightning Resistance","8%"],["Physical Resistance","8%"],["Necrotic Resistance","2%"],["Poison Resistance","2%"],["Void Resistance","2%"]]},{"header":"","type":"kv","rows":[["Increased Healing Effectiveness","25%"],["Increased Cooldown Recovery Speed","16%"],["Damage Reflected","0%"],["Increased Companion Revive Speed","65%"],["Increased Companion Revive Range","0%"]]},{"header":"","type":"matrix","text":"Melee\nSpell\nBow\nThrowing\nDoT\nAttack Speed\n48%\n–\n48%\n48%\n–\nCast Speed\n–\n85%\n–\n–\n–"},{"header":"","type":"matrix","text":"Melee\nSpell\nBow\nThrowing\nDoT\nCritical Chance\n13%\n13%\n13%\n13%\n–\nCritical Multiplier\n222%\n222%\n222%\n222%\n–"},{"header":"Damage","type":"matrix","text":"Damage\nMelee\nSpell\nBow\nThrowing\nDoT\nAdaptive Damage\n56\n99\n32\n0\n0"},{"header":"Damage","type":"matrix","text":"Damage\nMelee\nSpell\nBow\nThrowing\nDoT\n+ Physical Damage\n0\n0\n0\n0\n0\n% Physical Damage\n437%\n511%\n387%\n387%\n387%\n+ Fire Damage\n0\n0\n0\n0\n0\n% Fire Damage\n583%\n657%\n533%\n533%\n533%\n+ Cold Damage\n0\n0\n0\n0\n0\n% Cold Damage\n437%\n511%\n387%\n387%\n387%\n+ Lightning Damage\n0\n0\n0\n0\n0\n% Lightning Damage\n437%\n511%\n387%\n387%\n387%\n+ Necrotic Damage\n0\n0\n0\n0\n0\n% Necrotic Damage\n437%\n511%\n387%\n387%\n387%\n+ Void Damage\n0\n0\n0\n0\n0\n% Void Damage\n437%\n511%\n387%\n387%\n387%\n+ Poison Damage\n0\n0\n0\n0\n0\n% Poison Damage\n437%\n511%\n387%\n387%\n387%"},{"header":"Ailments","type":"matrix","text":"Ailments\nMelee\nSpell\nBow\nThrowing\nDoT\nBleed Chance\n0%\n0%\n0%\n0%\n0%\nBleed Damage\n258\n258\n258\n258\n258\nBleed Duration\n0%\n0%\n0%\n0%\n0%\nPoison Chance\n0%\n0%\n0%\n0%\n0%\nPoison Damage\n136\n136\n136\n136\n136\nPoison Duration\n0%\n0%\n0%\n0%\n0%\nIgnite Chance\n163%\n163%\n163%\n163%\n163%\nIgnite Damage\n253\n253\n253\n253\n253\nIgnite Duration\n0%\n0%\n0%\n0%\n0%\nFrostbite Chance\n0%\n0%\n0%\n0%\n0%\nFrostbite Damage\n244\n244\n244\n244\n244\nFrostbite Duration\n0%\n0%\n0%\n0%\n0%\nElectrify Chance\n0%\n0%\n0%\n0%\n0%\nElectrify Damage\n214\n214\n214\n214\n214\nElectrify Duration\n0%\n0%\n0%\n0%\n0%\nDoom Chance\n0%\n0%\n0%\n0%\n0%\nDoom Damage\n1948\n1948\n1948\n1948\n1948\nDoom Duration\n0%\n0%\n0%\n0%\n0%\nDamned Chance\n0%\n0%\n0%\n0%\n0%\nDamned Damage\n170\n170\n170\n170\n170\nDamned Duration\n0%\n0%\n0%\n0%\n0%\nTime Rot Chance\n0%\n0%\n0%\n0%\n0%\nTime Rot Damage\n292\n292\n292\n292\n292\nTime Rot Duration\n0%\n0%\n0%\n0%\n0%\nWitchfire Chance\n0%\n0%\n0%\n0%\n0%\nWitchfire Damage\n2922\n2922\n2922\n2922\n2922\nWitchfire Duration\n0%\n0%\n0%\n0%\n0%\nPlague Chance\n0%\n0%\n0%\n0%\n0%\nPlague Damage\n731\n731\n731\n731\n731\nPlague Duration\n0%\n0%\n0%\n0%\n0%\nShock Chance\n0%\n0%\n0%\n0%\n0%\nShock Duration\n0%\n0%\n0%\n0%\n0%\nSlow Chance\n0%\n0%\n0%\n0%\n0%\nSlow Duration\n0%\n0%\n0%\n0%\n0%\nBlind Chance\n0%\n0%\n0%\n0%\n0%\nBlind Duration\n0%\n0%\n0%\n0%\n0%\nFrailty Chance\n0%\n0%\n0%\n0%\n0%\nFrailty Duration\n0%\n0%\n0%\n0%\n0%\nShred Armor Chance\n0%\n0%\n0%\n0%\n0%\nShred Armor Effect\n0%\n0%\n0%\n0%\n0%\nShred Armor Duration\n0%\n0%\n0%\n0%\n0%\nShred Fire Resistance Chance\n0%\n0%\n0%\n0%\n0%\nShred Fire Resistance Effect\n0%\n0%\n0%\n0%\n0%\nShred Fire Resistance Duration\n0%\n0%\n0%\n0%\n0%\nShred Cold Resistance Chance\n0%\n0%\n0%\n0%\n0%\nShred Cold Resistance Effect\n0%\n0%\n0%\n0%\n0%\nShred Cold Resistance Duration\n0%\n0%\n0%\n0%\n0%\nShred Lightning Resistance Chance\n0%\n0%\n0%\n0%\n0%\nShred Lightning Resistance Effect\n0%\n0%\n0%\n0%\n0%\nShred Lightning Resistance Duration\n0%\n0%\n0%\n0%\n0%\nShred Physical Resistance Chance\n0%\n0%\n0%\n0%\n0%\nShred Physical Resistance Effect\n0%\n0%\n0%\n0%\n0%\nShred Physical Resistance Duration\n0%\n0%\n0%\n0%\n0%\nShred Necrotic Resistance Chance\n0%\n0%\n0%\n0%\n0%\nShred Necrotic Resistance Effect\n0%\n0%\n0%\n0%\n0%\nShred Necrotic Resistance Duration\n0%\n0%\n0%\n0%\n0%\nShred Poison Resistance Chance\n0%\n0%\n0%\n0%\n0%\nShred Poison Resistance Effect\n0%\n0%\n0%\n0%\n0%\nShred Poison Resistance Duration\n0%\n0%\n0%\n0%\n0%\nShred Void Resistance Chance\n0%\n0%\n0%\n0%\n0%\nShred Void Resistance Effect\n0%\n0%\n0%\n0%\n0%\nShred Void Resistance Duration\n0%\n0%\n0%\n0%\n0%\nChill Chance\n0%\n0%\n0%\n0%\n0%\nChill Duration\n0%\n0%\n0%\n0%\n0%\nFreeze Rate Multiplier\n0%\n0%\n0%\n0%\n0%"},{"header":"Other","type":"matrix","text":"Other\nMelee\nSpell\nBow\nThrowing\nDoT\nIncreased Stun Chance\n0%\n0%\n0%\n0%\n–\nIncreased Stun Duration\n0%\n0%\n0%\n0%\n–"}],"Other":[{"header":"","type":"kv","rows":[["Potion Slots","4"],["Potion Refill On Kill","0%"],["Mana Efficiency","0%"],["Increased Healing Effectiveness","25%"],["Increased Cooldown Recovery Speed","19%"]]},{"header":"","type":"kv","rows":[["Damage Reflected","0%"],["Damage Dealt To Attackers","0"],["Chance To Chill Attackers","0%"],["Chance To Slow Attackers","0%"],["Chance To Shock Attackers","0%"]]},{"header":"","type":"kv","rows":[["Double Damage Chance","0%"]]}]}}
