{"meta":{"buildId":"o3Zlpkxd","url":"https://www.lastepochtools.com/planner/o3Zlpkxd","title":"Necromancer, level 98 (Season 4: Shattered Omens) - Last Epoch Build Planner","scrapedAt":"2026-04-26T12:07:07.542Z"},"items":{"item-chest":{"tabs":[{"cls":"tab items used selected","text":"Item (38)"},{"cls":"tab prefixes used","text":"Prefix 1 (46)"},{"cls":"tab prefixes","text":"Prefix 2 (46)"},{"cls":"tab suffixes used","text":"Suffix 1 (17)"},{"cls":"tab suffixes","text":"Suffix 2 (17)"},{"cls":"tab enchants","text":"Enchanted Affix 1 (0)"},{"cls":"tab enchants","text":"Enchanted Affix 2 (0)"},{"cls":"tab sealedAffixes","text":"Sealed Affix (0)"},{"cls":"tab primordialAffixes locked","text":"Primordial Affix (0)"},{"cls":"tab corruptedAffixes","text":"Corrupted Affix (78)"}],"affixes":[{"tab":"Prefix 1 (46)","tabCls":"tab prefixes used","name":"Mana","tiers":[{"cls":"affix tier-header","text":"ManaAdded"},{"cls":"affix","text":"Tier 19 to 15"},{"cls":"affix","text":"Tier 216 to 26"},{"cls":"affix","text":"Tier 327 to 38"},{"cls":"affix","text":"Tier 439 to 52"},{"cls":"affix","text":"Tier 554 to 75"},{"cls":"affix selected","text":"Tier 6105 to 135"},{"cls":"affix","text":"Tier 7136 to 180"},{"cls":"affix","text":"Tier 8285 to 360"}],"requiredLevel":null,"requiredItemClass":null,"weight":{"value":1,"label":""}},{"tab":"Suffix 1 (17)","tabCls":"tab suffixes used","name":"Necrotic Resistance","tiers":[{"cls":"affix tier-header","text":"Necrotic ResistanceAdded"},{"cls":"affix","text":"Tier 18% to 14%"},{"cls":"affix","text":"Tier 215% to 21%"},{"cls":"affix","text":"Tier 322% to 32%"},{"cls":"affix selected","text":"Tier 433% to 43%"},{"cls":"affix","text":"Tier 545% to 68%"},{"cls":"affix","text":"Tier 675% to 90%"},{"cls":"affix","text":"Tier 792% to 112%"},{"cls":"affix","text":"Tier 8180% to 225%"}],"requiredLevel":null,"requiredItemClass":null,"weight":{"value":1,"label":""}}]},"item-head":{"tabs":[{"cls":"tab items used selected","text":"Item (30)"},{"cls":"tab prefixes used","text":"Prefix 1 (43)"},{"cls":"tab prefixes","text":"Prefix 2 (43)"},{"cls":"tab suffixes","text":"Suffix 1 (19)"},{"cls":"tab suffixes","text":"Suffix 2 (19)"},{"cls":"tab enchants","text":"Enchanted Affix 1 (0)"},{"cls":"tab enchants","text":"Enchanted Affix 2 (0)"},{"cls":"tab sealedAffixes","text":"Sealed Affix (0)"},{"cls":"tab primordialAffixes locked","text":"Primordial Affix (0)"},{"cls":"tab corruptedAffixes used","text":"Corrupted Affix (76)"}],"affixes":[{"tab":"Prefix 1 (43)","tabCls":"tab prefixes used","name":"Strength","tiers":[{"cls":"affix tier-header","text":"StrengthAdded"},{"cls":"affix","text":"Tier 11"},{"cls":"affix","text":"Tier 22"},{"cls":"affix","text":"Tier 33 to 4"},{"cls":"affix selected","text":"Tier 45 to 6"},{"cls":"affix","text":"Tier 57 to 8"},{"cls":"affix","text":"Tier 611 to 13"},{"cls":"affix","text":"Tier 714 to 16"},{"cls":"affix","text":"Tier 824 to 28"}],"requiredLevel":null,"requiredItemClass":null,"weight":{"value":1,"label":""}},{"tab":"Corrupted Affix (76)","tabCls":"tab corruptedAffixes used","name":"Added Attunement and Increased Mana Regen","tiers":[{"cls":"affix tier-header","text":"AttunementAddedMana RegenIncreased"},{"cls":"affix","text":"Tier 148% to 9%"},{"cls":"affix","text":"Tier 2510% to 11%"},{"cls":"affix","text":"Tier 3512% to 13%"},{"cls":"affix selected","text":"Tier 4614% to 15%"},{"cls":"affix","text":"Tier 5616% to 17%"},{"cls":"affix","text":"Tier 6718% to 19%"},{"cls":"affix","text":"Tier 7720% to 22%"},{"cls":"affix","text":"Tier 81028% to 32%"}],"requiredLevel":null,"requiredItemClass":null,"weight":{"value":1,"label":""}}]},"item-hands":{"tabs":[{"cls":"tab items used selected","text":"Item (46)"},{"cls":"tab prefixes used","text":"Prefix 1 (23)"},{"cls":"tab prefixes","text":"Prefix 2 (23)"},{"cls":"tab suffixes","text":"Suffix 1 (21)"},{"cls":"tab suffixes","text":"Suffix 2 (21)"},{"cls":"tab enchants","text":"Enchanted Affix 1 (0)"},{"cls":"tab enchants","text":"Enchanted Affix 2 (0)"},{"cls":"tab sealedAffixes","text":"Sealed Affix (0)"},{"cls":"tab primordialAffixes locked","text":"Primordial Affix (0)"},{"cls":"tab corruptedAffixes used","text":"Corrupted Affix (55)"}],"affixes":[{"tab":"Prefix 1 (23)","tabCls":"tab prefixes used","name":"Mana","tiers":[{"cls":"affix tier-header","text":"ManaAdded"},{"cls":"affix","text":"Tier 16 to 10"},{"cls":"affix","text":"Tier 211 to 17"},{"cls":"affix","text":"Tier 318 to 25"},{"cls":"affix","text":"Tier 426 to 35"},{"cls":"affix","text":"Tier 536 to 50"},{"cls":"affix","text":"Tier 670 to 90"},{"cls":"affix selected","text":"Tier 791 to 120"},{"cls":"affix","text":"Tier 8190 to 240"}],"requiredLevel":null,"requiredItemClass":null,"weight":{"value":1,"label":""}},{"tab":"Corrupted Affix (55)","tabCls":"tab corruptedAffixes used","name":"Physical Resistance and Void Resistance","tiers":[{"cls":"affix tier-header","text":"Physical ResistanceAddedVoid ResistanceAdded"},{"cls":"affix","text":"Tier 114%14%"},{"cls":"affix","text":"Tier 215%15%"},{"cls":"affix","text":"Tier 316%16%"},{"cls":"affix selected","text":"Tier 417%17%"},{"cls":"affix","text":"Tier 518%18%"},{"cls":"affix","text":"Tier 619%19%"},{"cls":"affix","text":"Tier 720% to 21%20% to 21%"},{"cls":"affix","text":"Tier 830% to 35%30% to 35%"}],"requiredLevel":null,"requiredItemClass":null,"weight":{"value":0.5,"label":""}}]},"item-feet":{"tabs":[{"cls":"tab items used selected","text":"Item (42)"},{"cls":"tab prefixes used","text":"Prefix 1 (11)"},{"cls":"tab prefixes used","text":"Prefix 2 (11)"},{"cls":"tab suffixes","text":"Suffix 1 (17)"},{"cls":"tab suffixes","text":"Suffix 2 (17)"},{"cls":"tab enchants","text":"Enchanted Affix 1 (0)"},{"cls":"tab enchants","text":"Enchanted Affix 2 (0)"},{"cls":"tab sealedAffixes","text":"Sealed Affix (0)"},{"cls":"tab primordialAffixes locked","text":"Primordial Affix (0)"},{"cls":"tab corruptedAffixes","text":"Corrupted Affix (39)"}],"affixes":[{"tab":"Prefix 1 (11)","tabCls":"tab prefixes used","name":"Intelligence","tiers":[{"cls":"affix tier-header","text":"IntelligenceAdded"},{"cls":"affix","text":"Tier 11"},{"cls":"affix","text":"Tier 22"},{"cls":"affix","text":"Tier 33 to 4"},{"cls":"affix","text":"Tier 45 to 6"},{"cls":"affix","text":"Tier 57 to 8"},{"cls":"affix selected","text":"Tier 611 to 13"},{"cls":"affix","text":"Tier 714 to 16"},{"cls":"affix","text":"Tier 824 to 28"}],"requiredLevel":null,"requiredItemClass":null,"weight":{"value":1,"label":""}},{"tab":"Prefix 2 (11)","tabCls":"tab prefixes used","name":"Movement Speed","tiers":[{"cls":"affix tier-header","text":"Movement SpeedIncreased"},{"cls":"affix","text":"Tier 15% to 7%"},{"cls":"affix","text":"Tier 28% to 9%"},{"cls":"affix","text":"Tier 310% to 11%"},{"cls":"affix","text":"Tier 412% to 14%"},{"cls":"affix selected","text":"Tier 515% to 18%"},{"cls":"affix","text":"Tier 622% to 25%"},{"cls":"affix","text":"Tier 726% to 30%"},{"cls":"affix","text":"Tier 843% to 48%"}],"requiredLevel":null,"requiredItemClass":null,"weight":{"value":1,"label":""}}]},"item-waist":{"tabs":[{"cls":"tab items used selected","text":"Item (38)"},{"cls":"tab prefixes used","text":"Prefix 1 (26)"},{"cls":"tab prefixes used","text":"Prefix 2 (26)"},{"cls":"tab suffixes used","text":"Suffix 1 (21)"},{"cls":"tab suffixes used","text":"Suffix 2 (21)"},{"cls":"tab enchants","text":"Enchanted Affix 1 (0)"},{"cls":"tab enchants","text":"Enchanted Affix 2 (0)"},{"cls":"tab sealedAffixes used","text":"Sealed Affix (49)"},{"cls":"tab primordialAffixes locked","text":"Primordial Affix (0)"},{"cls":"tab corruptedAffixes used","text":"Corrupted Affix (64)"}],"affixes":[{"tab":"Prefix 1 (26)","tabCls":"tab prefixes used","name":"Minion Damage","tiers":[{"cls":"affix tier-header","text":"Minion DamageIncreased"},{"cls":"affix","text":"Tier 16% to 12%"},{"cls":"affix","text":"Tier 213% to 21%"},{"cls":"affix","text":"Tier 322% to 30%"},{"cls":"affix","text":"Tier 431% to 39%"},{"cls":"affix","text":"Tier 540% to 60%"},{"cls":"affix selected","text":"Tier 675% to 95%"},{"cls":"affix","text":"Tier 796% to 120%"},{"cls":"affix","text":"Tier 8192% to 240%"}],"requiredLevel":null,"requiredItemClass":null,"weight":{"value":1,"label":""}},{"tab":"Prefix 2 (26)","tabCls":"tab prefixes used","name":"Minion Health","tiers":[{"cls":"affix tier-header","text":"Minion HealthIncreased"},{"cls":"affix","text":"Tier 115% to 35%"},{"cls":"affix","text":"Tier 236% to 55%"},{"cls":"affix","text":"Tier 356% to 75%"},{"cls":"affix","text":"Tier 476% to 100%"},{"cls":"affix selected","text":"Tier 5101% to 150%"},{"cls":"affix","text":"Tier 6190% to 230%"},{"cls":"affix","text":"Tier 7231% to 300%"},{"cls":"affix","text":"Tier 8500% to 600%"}],"requiredLevel":null,"requiredItemClass":null,"weight":{"value":0.6,"label":""}},{"tab":"Suffix 1 (21)","tabCls":"tab suffixes used","name":"Elemental Resistance","tiers":[{"cls":"affix tier-header","text":"Elemental ResistanceAdded"},{"cls":"affix","text":"Tier 14% to 5%"},{"cls":"affix","text":"Tier 26% to 8%"},{"cls":"affix","text":"Tier 39% to 11%"},{"cls":"affix","text":"Tier 412% to 15%"},{"cls":"affix selected","text":"Tier 516% to 20%"},{"cls":"affix","text":"Tier 624% to 30%"},{"cls":"affix","text":"Tier 731% to 40%"},{"cls":"affix","text":"Tier 864% to 75%"}],"requiredLevel":null,"requiredItemClass":null,"weight":{"value":0.7,"label":""}},{"tab":"Suffix 2 (21)","tabCls":"tab suffixes used","name":"Hybrid Health","tiers":[{"cls":"affix tier-header","text":"HealthAddedHealthIncreased"},{"cls":"affix","text":"Tier 114 to 213%"},{"cls":"affix","text":"Tier 222 to 293%"},{"cls":"affix","text":"Tier 330 to 374%"},{"cls":"affix","text":"Tier 438 to 454%"},{"cls":"affix selected","text":"Tier 546 to 685%"},{"cls":"affix","text":"Tier 685 to 1056% to 7%"},{"cls":"affix","text":"Tier 7106 to 1358% to 10%"},{"cls":"affix","text":"Tier 8205 to 24315% to 18%"}],"requiredLevel":null,"requiredItemClass":null,"weight":{"value":0.1,"label":""}},{"tab":"Sealed Affix (49)","tabCls":"tab sealedAffixes used","name":"Lightning Damage","tiers":[{"cls":"affix tier-header","text":"Lightning DamageIncreased"},{"cls":"affix","text":"Tier 16% to 12%"},{"cls":"affix","text":"Tier 213% to 21%"},{"cls":"affix","text":"Tier 322% to 30%"},{"cls":"affix","text":"Tier 431% to 39%"},{"cls":"affix selected","text":"Tier 540% to 60%"},{"cls":"affix","text":"Tier 675% to 95%"},{"cls":"affix","text":"Tier 796% to 120%"},{"cls":"affix","text":"Tier 8192% to 240%"}],"requiredLevel":null,"requiredItemClass":null,"weight":{"value":0.5,"label":""}},{"tab":"Corrupted Affix (64)","tabCls":"tab corruptedAffixes used","name":"Experimental Traversal Cooldown Recovery on Potion Use","tiers":[{"cls":"affix tier-header","text":"Seconds of Traversal Skill Cooldowns Recovered on Potion UseAddedIncreased Chance To Find PotionsAdded"},{"cls":"affix selected","text":"Tier 10.516% to 20%"},{"cls":"affix","text":"Tier 20.621% to 25%"},{"cls":"affix","text":"Tier 30.726% to 32%"},{"cls":"affix","text":"Tier 40.8 to 0.933% to 40%"},{"cls":"affix","text":"Tier 51.1 to 1.241% to 50%"},{"cls":"affix","text":"Tier 61.4 to 1.570% to 79%"},{"cls":"affix","text":"Tier 71.6 to 1.880% to 100%"},{"cls":"affix","text":"Tier 82.2 to 2.7160% to 200%"}],"requiredLevel":null,"requiredItemClass":null,"weight":{"value":1,"label":""}}]},"item-weapon1":{"tabs":[{"cls":"tab items used selected","text":"Item (35)"},{"cls":"tab prefixes used","text":"Prefix 1 (27)"},{"cls":"tab prefixes used","text":"Prefix 2 (27)"},{"cls":"tab suffixes used","text":"Suffix 1 (19)"},{"cls":"tab suffixes used","text":"Suffix 2 (19)"},{"cls":"tab enchants","text":"Enchanted Affix 1 (0)"},{"cls":"tab enchants","text":"Enchanted Affix 2 (0)"},{"cls":"tab sealedAffixes","text":"Sealed Affix (47)"},{"cls":"tab primordialAffixes locked","text":"Primordial Affix (0)"},{"cls":"tab corruptedAffixes used","text":"Corrupted Affix (59)"}],"affixes":[{"tab":"Prefix 1 (27)","tabCls":"tab prefixes used","name":"Mana and Mana Spent Gained as Ward","tiers":[{"cls":"affix tier-header","text":"ManaAddedMana Spent Gained as WardAdded"},{"cls":"affix","text":"Tier 118 to 3118% to 26%"},{"cls":"affix","text":"Tier 233 to 4627% to 37%"},{"cls":"affix","text":"Tier 348 to 6238% to 49%"},{"cls":"affix","text":"Tier 464 to 8251% to 64%"},{"cls":"affix selected","text":"Tier 584 to 11066% to 91%"},{"cls":"affix","text":"Tier 6137 to 165119% to 146%"},{"cls":"affix","text":"Tier 7166 to 219148% to 183%"},{"cls":"affix","text":"Tier 8351 to 439293% to 366%"}],"requiredLevel":null,"requiredItemClass":null,"weight":{"value":0.7,"label":""}},{"tab":"Prefix 2 (27)","tabCls":"tab prefixes used","name":"Mana and Mana Regen","tiers":[{"cls":"affix tier-header","text":"ManaAddedMana RegenIncreased"},{"cls":"affix","text":"Tier 118 to 3111% to 15%"},{"cls":"affix","text":"Tier 233 to 4616% to 22%"},{"cls":"affix","text":"Tier 348 to 6224% to 29%"},{"cls":"affix","text":"Tier 464 to 8231% to 37%"},{"cls":"affix selected","text":"Tier 584 to 11038% to 46%"},{"cls":"affix","text":"Tier 6137 to 16555% to 64%"},{"cls":"affix","text":"Tier 7166 to 21966% to 77%"},{"cls":"affix","text":"Tier 8351 to 439123% to 154%"}],"requiredLevel":null,"requiredItemClass":null,"weight":{"value":1,"label":""}},{"tab":"Suffix 1 (19)","tabCls":"tab suffixes used","name":"Minion Melee and Spell Damage","tiers":[{"cls":"affix tier-header","text":"Minion Melee DamageAddedMinion Spell DamageAdded"},{"cls":"affix","text":"Tier 15 to 75 to 7"},{"cls":"affix","text":"Tier 29 to 119 to 11"},{"cls":"affix","text":"Tier 313 to 1613 to 16"},{"cls":"affix","text":"Tier 418 to 2218 to 22"},{"cls":"affix","text":"Tier 524 to 3124 to 31"},{"cls":"affix selected","text":"Tier 638 to 4638 to 46"},{"cls":"affix","text":"Tier 748 to 5948 to 59"},{"cls":"affix","text":"Tier 882 to 10282 to 102"}],"requiredLevel":null,"requiredItemClass":null,"weight":{"value":0.45,"label":""}},{"tab":"Suffix 2 (19)","tabCls":"tab suffixes used","name":"Minion Spell and Bow Damage","tiers":[{"cls":"affix tier-header","text":"Minion Spell DamageAddedMinion Bow DamageAdded"},{"cls":"affix","text":"Tier 15 to 75 to 7"},{"cls":"affix","text":"Tier 29 to 119 to 11"},{"cls":"affix","text":"Tier 313 to 1613 to 16"},{"cls":"affix","text":"Tier 418 to 2218 to 22"},{"cls":"affix selected","text":"Tier 524 to 3124 to 31"},{"cls":"affix","text":"Tier 638 to 4638 to 46"},{"cls":"affix","text":"Tier 748 to 5948 to 59"},{"cls":"affix","text":"Tier 882 to 10282 to 102"}],"requiredLevel":null,"requiredItemClass":null,"weight":{"value":0.3,"label":""}},{"tab":"Corrupted Affix (59)","tabCls":"tab corruptedAffixes used","name":"Increased Spell Area of Effect and Added Spell Mana Cost","tiers":[{"cls":"affix tier-header","text":"Increased Area for Spell Area SkillsAddedMana Cost for Spell SkillsAdded"},{"cls":"affix","text":"Tier 168% to 77%3"},{"cls":"affix","text":"Tier 279% to 88%3"},{"cls":"affix","text":"Tier 390% to 98%5"},{"cls":"affix selected","text":"Tier 4101% to 109%5"},{"cls":"affix","text":"Tier 5112% to 120%5"},{"cls":"affix","text":"Tier 6123% to 131%8"},{"cls":"affix","text":"Tier 7134% to 137%8"},{"cls":"affix","text":"Tier 8191% to 205%16"}],"requiredLevel":null,"requiredItemClass":null,"weight":{"value":0.5,"label":""}}]},"item-weapon2":{"tabs":[{"cls":"tab items selected","text":"Item (43)"},{"cls":"tab prefixes","text":"Prefix 1 (13)"},{"cls":"tab prefixes","text":"Prefix 2 (13)"},{"cls":"tab suffixes","text":"Suffix 1 (18)"},{"cls":"tab suffixes","text":"Suffix 2 (18)"},{"cls":"tab enchants","text":"Enchanted Affix 1 (0)"},{"cls":"tab enchants","text":"Enchanted Affix 2 (0)"},{"cls":"tab sealedAffixes","text":"Sealed Affix (31)"},{"cls":"tab primordialAffixes locked","text":"Primordial Affix (0)"},{"cls":"tab corruptedAffixes","text":"Corrupted Affix (13)"}],"affixes":[]},"item-amulet":{"tabs":[{"cls":"tab items selected used","text":"Item (49)"},{"cls":"tab prefixes used","text":"Prefix 1 (34)"},{"cls":"tab prefixes","text":"Prefix 2 (34)"},{"cls":"tab suffixes","text":"Suffix 1 (18)"},{"cls":"tab suffixes","text":"Suffix 2 (18)"},{"cls":"tab enchants","text":"Enchanted Affix 1 (0)"},{"cls":"tab enchants","text":"Enchanted Affix 2 (0)"},{"cls":"tab sealedAffixes","text":"Sealed Affix (0)"},{"cls":"tab primordialAffixes locked","text":"Primordial Affix (0)"},{"cls":"tab corruptedAffixes used","text":"Corrupted Affix (58)"}],"affixes":[{"tab":"Prefix 1 (34)","tabCls":"tab prefixes used","name":"Minion Area and Damage","tiers":[{"cls":"affix tier-header","text":"Increased Area for Minion Area SkillsAddedMinion DamageIncreased"},{"cls":"affix","text":"Tier 17% to 8%6% to 12%"},{"cls":"affix","text":"Tier 29% to 11%13% to 21%"},{"cls":"affix","text":"Tier 312% to 14%23% to 32%"},{"cls":"affix","text":"Tier 415% to 18%33% to 41%"},{"cls":"affix","text":"Tier 519% to 21%42% to 58%"},{"cls":"affix","text":"Tier 627% to 32%76% to 94%"},{"cls":"affix selected","text":"Tier 733% to 39%95% to 123%"},{"cls":"affix","text":"Tier 864% to 76%205% to 246%"}],"requiredLevel":null,"requiredItemClass":null,"weight":{"value":0.3,"label":""}},{"tab":"Corrupted Affix (58)","tabCls":"tab corruptedAffixes used","name":"Physical Damage","tiers":[{"cls":"affix tier-header","text":"Physical DamageIncreased"},{"cls":"affix selected","text":"Tier 17% to 14%"},{"cls":"affix","text":"Tier 215% to 25%"},{"cls":"affix","text":"Tier 326% to 35%"},{"cls":"affix","text":"Tier 436% to 46%"},{"cls":"affix","text":"Tier 547% to 70%"},{"cls":"affix","text":"Tier 688% to 111%"},{"cls":"affix","text":"Tier 7112% to 140%"},{"cls":"affix","text":"Tier 8225% to 281%"}],"requiredLevel":null,"requiredItemClass":null,"weight":{"value":1,"label":""}}]},"item-ring1":{"tabs":[{"cls":"tab items used selected","text":"Item (45)"},{"cls":"tab prefixes used","text":"Prefix 1 (25)"},{"cls":"tab prefixes","text":"Prefix 2 (25)"},{"cls":"tab suffixes used","text":"Suffix 1 (17)"},{"cls":"tab suffixes","text":"Suffix 2 (17)"},{"cls":"tab enchants","text":"Enchanted Affix 1 (0)"},{"cls":"tab enchants","text":"Enchanted Affix 2 (0)"},{"cls":"tab sealedAffixes","text":"Sealed Affix (0)"},{"cls":"tab primordialAffixes locked","text":"Primordial Affix (0)"},{"cls":"tab corruptedAffixes","text":"Corrupted Affix (57)"}],"affixes":[{"tab":"Prefix 1 (25)","tabCls":"tab prefixes used","name":"Intelligence","tiers":[{"cls":"affix tier-header","text":"IntelligenceAdded"},{"cls":"affix","text":"Tier 11"},{"cls":"affix","text":"Tier 22"},{"cls":"affix","text":"Tier 33 to 4"},{"cls":"affix","text":"Tier 45 to 6"},{"cls":"affix","text":"Tier 57 to 8"},{"cls":"affix","text":"Tier 611 to 13"},{"cls":"affix selected","text":"Tier 714 to 16"},{"cls":"affix","text":"Tier 824 to 28"}],"requiredLevel":null,"requiredItemClass":null,"weight":{"value":1,"label":""}},{"tab":"Suffix 1 (17)","tabCls":"tab suffixes used","name":"Necrotic Resistance","tiers":[{"cls":"affix tier-header","text":"Necrotic ResistanceAdded"},{"cls":"affix","text":"Tier 15% to 9%"},{"cls":"affix","text":"Tier 210% to 14%"},{"cls":"affix","text":"Tier 315% to 21%"},{"cls":"affix","text":"Tier 422% to 29%"},{"cls":"affix selected","text":"Tier 530% to 45%"},{"cls":"affix","text":"Tier 650% to 60%"},{"cls":"affix","text":"Tier 761% to 75%"},{"cls":"affix","text":"Tier 8120% to 150%"}],"requiredLevel":null,"requiredItemClass":null,"weight":{"value":1,"label":""}}]},"item-ring2":{"tabs":[{"cls":"tab items used selected","text":"Item (45)"},{"cls":"tab prefixes used","text":"Prefix 1 (25)"},{"cls":"tab prefixes","text":"Prefix 2 (25)"},{"cls":"tab suffixes used","text":"Suffix 1 (17)"},{"cls":"tab suffixes","text":"Suffix 2 (17)"},{"cls":"tab enchants","text":"Enchanted Affix 1 (0)"},{"cls":"tab enchants","text":"Enchanted Affix 2 (0)"},{"cls":"tab sealedAffixes","text":"Sealed Affix (0)"},{"cls":"tab primordialAffixes locked","text":"Primordial Affix (0)"},{"cls":"tab corruptedAffixes","text":"Corrupted Affix (57)"}],"affixes":[{"tab":"Prefix 1 (25)","tabCls":"tab prefixes used","name":"Intelligence","tiers":[{"cls":"affix tier-header","text":"IntelligenceAdded"},{"cls":"affix","text":"Tier 11"},{"cls":"affix","text":"Tier 22"},{"cls":"affix","text":"Tier 33 to 4"},{"cls":"affix","text":"Tier 45 to 6"},{"cls":"affix","text":"Tier 57 to 8"},{"cls":"affix","text":"Tier 611 to 13"},{"cls":"affix selected","text":"Tier 714 to 16"},{"cls":"affix","text":"Tier 824 to 28"}],"requiredLevel":null,"requiredItemClass":null,"weight":{"value":1,"label":""}},{"tab":"Suffix 1 (17)","tabCls":"tab suffixes used","name":"Necrotic Resistance","tiers":[{"cls":"affix tier-header","text":"Necrotic ResistanceAdded"},{"cls":"affix","text":"Tier 15% to 9%"},{"cls":"affix","text":"Tier 210% to 14%"},{"cls":"affix","text":"Tier 315% to 21%"},{"cls":"affix","text":"Tier 422% to 29%"},{"cls":"affix selected","text":"Tier 530% to 45%"},{"cls":"affix","text":"Tier 650% to 60%"},{"cls":"affix","text":"Tier 761% to 75%"},{"cls":"affix","text":"Tier 8120% to 150%"}],"requiredLevel":null,"requiredItemClass":null,"weight":{"value":1,"label":""}}]},"item-relic":{"tabs":[{"cls":"tab items used selected","text":"Item (39)"},{"cls":"tab prefixes used","text":"Prefix 1 (36)"},{"cls":"tab prefixes","text":"Prefix 2 (36)"},{"cls":"tab suffixes","text":"Suffix 1 (14)"},{"cls":"tab suffixes","text":"Suffix 2 (14)"},{"cls":"tab enchants","text":"Enchanted Affix 1 (0)"},{"cls":"tab enchants","text":"Enchanted Affix 2 (0)"},{"cls":"tab sealedAffixes","text":"Sealed Affix (0)"},{"cls":"tab primordialAffixes","text":"Primordial Affix (0)"},{"cls":"tab corruptedAffixes used","text":"Corrupted Affix (65)"}],"affixes":[{"tab":"Prefix 1 (36)","tabCls":"tab prefixes used","name":"Level of Summon Skeletal Mage","tiers":[{"cls":"affix tier-header","text":"Level of Summon Skeletal MageAddedMinion DamageIncreased"},{"cls":"affix","text":"Tier 115% to 10%"},{"cls":"affix","text":"Tier 2111% to 20%"},{"cls":"affix","text":"Tier 3121% to 30%"},{"cls":"affix","text":"Tier 4131% to 40%"},{"cls":"affix selected","text":"Tier 5241% to 60%"},{"cls":"affix","text":"Tier 6371% to 80%"},{"cls":"affix","text":"Tier 7481% to 100%"},{"cls":"affix","text":"Tier 86160% to 200%"}],"requiredLevel":null,"requiredItemClass":null,"weight":{"value":0.14,"label":""}},{"tab":"Corrupted Affix (65)","tabCls":"tab corruptedAffixes used","name":"Added Intelligence and Ward Per Second","tiers":[{"cls":"affix tier-header","text":"IntelligenceAddedWard per SecondAdded"},{"cls":"affix","text":"Tier 147 to 8"},{"cls":"affix selected","text":"Tier 259 to 10"},{"cls":"affix","text":"Tier 3511 to 12"},{"cls":"affix","text":"Tier 4613 to 14"},{"cls":"affix","text":"Tier 5615 to 16"},{"cls":"affix","text":"Tier 6717 to 18"},{"cls":"affix","text":"Tier 7719 to 21"},{"cls":"affix","text":"Tier 81025 to 30"}],"requiredLevel":null,"requiredItemClass":null,"weight":{"value":1,"label":""}}]}}}
